odoo9_addon_pos_barcode_tare-9.0.0.0.1.99.dev28-py3.6-nspkg.pth
odoo_addons/pos_barcode_tare/README.rst
odoo_addons/pos_barcode_tare/__init__.py
odoo_addons/pos_barcode_tare/__openerp__.py
odoo_addons/pos_barcode_tare/pos_barcode_tare.xml
odoo_addons/pos_barcode_tare/data/barcode_rule.xml
odoo_addons/pos_barcode_tare/demo/pos_barcode_tare_demo.xml
odoo_addons/pos_barcode_tare/i18n/ca.po
odoo_addons/pos_barcode_tare/i18n/es.po
odoo_addons/pos_barcode_tare/i18n/fr_CH.po
odoo_addons/pos_barcode_tare/i18n/pos_barcode_tare.pot
odoo_addons/pos_barcode_tare/models/__init__.py
odoo_addons/pos_barcode_tare/models/barcode_rule.py
odoo_addons/pos_barcode_tare/models/pos_config.py
odoo_addons/pos_barcode_tare/readme/CONTRIBUTORS.rst
odoo_addons/pos_barcode_tare/readme/DESCRIPTION.rst
odoo_addons/pos_barcode_tare/readme/ROADMAP.rst
odoo_addons/pos_barcode_tare/readme/USAGE.rst
odoo_addons/pos_barcode_tare/static/description/POS_with_button.png
odoo_addons/pos_barcode_tare/static/description/icon.png
odoo_addons/pos_barcode_tare/static/description/index.html
odoo_addons/pos_barcode_tare/static/description/label.png
odoo_addons/pos_barcode_tare/static/description/null_weight.png
odoo_addons/pos_barcode_tare/static/description/ready_to_print.png
odoo_addons/pos_barcode_tare/static/description/zoom_action_widget.png
odoo_addons/pos_barcode_tare/static/src/css/pos_barcode_tare.css
odoo_addons/pos_barcode_tare/static/src/js/pos_barcode_tare.js
odoo_addons/pos_barcode_tare/static/src/xml/pos_barcode_tare.xml
odoo_addons/pos_barcode_tare/views/pos_config_view.xml
odoo9_addon_pos_barcode_tare-9.0.0.0.1.99.dev28.dist-info/METADATA
odoo9_addon_pos_barcode_tare-9.0.0.0.1.99.dev28.dist-info/WHEEL
odoo9_addon_pos_barcode_tare-9.0.0.0.1.99.dev28.dist-info/namespace_packages.txt
odoo9_addon_pos_barcode_tare-9.0.0.0.1.99.dev28.dist-info/top_level.txt
odoo9_addon_pos_barcode_tare-9.0.0.0.1.99.dev28.dist-info/RECORD
